.gitignore
.readthedocs.yml
.travis.yml
AUTHORS
LICENSE
MANIFEST.in
README.rst
dev-requirements.txt
setup.cfg
setup.py
tox.ini
docs/Makefile
docs/make.bat
docs/requirements.txt
docs/source/concepts.rst
docs/source/conf.py
docs/source/index.rst
docs/source/installation.rst
docs/source/api/index.rst
docs/source/api/metric.rst
docs/source/api/numerical.rst
docs/source/api/partial.rst
docs/source/api/tensor.rst
docs/source/examples/index.rst
riccipy/__init__.py
riccipy/metric.py
riccipy/numerical.py
riccipy/partial.py
riccipy/tensor.py
riccipy.egg-info/PKG-INFO
riccipy.egg-info/SOURCES.txt
riccipy.egg-info/dependency_links.txt
riccipy.egg-info/requires.txt
riccipy.egg-info/top_level.txt
riccipy/metrics/__init__.py
riccipy/metrics/anti_de_sitter_1.py
riccipy/metrics/anti_de_sitter_2.py
riccipy/metrics/bayin.py
riccipy/metrics/beckers_sinzinkayo_demaret_1.py
riccipy/metrics/beckers_sinzinkayo_demaret_2.py
riccipy/metrics/bertotti_robinson_1.py
riccipy/metrics/bertotti_robinson_2.py
riccipy/metrics/bertotti_robinson_3.py
riccipy/metrics/bertotti_robinson_4.py
riccipy/metrics/bianchi_1.py
riccipy/metrics/bianchi_2.py
riccipy/metrics/bondi_1.py
riccipy/metrics/bondi_2.py
riccipy/metrics/bondi_3.py
riccipy/metrics/boost_1.py
riccipy/metrics/boost_2.py
riccipy/metrics/boost_3.py
riccipy/metrics/buchdahl_land.py
riccipy/metrics/cmetric.py
riccipy/metrics/cross_const_curvature_1.py
riccipy/metrics/cross_const_curvature_2.py
riccipy/metrics/cross_const_curvature_3.py
riccipy/metrics/cross_const_curvature_4.py
riccipy/metrics/datta_1.py
riccipy/metrics/datta_2.py
riccipy/metrics/davidson.py
riccipy/metrics/de_sitter_1.py
riccipy/metrics/de_sitter_2.py
riccipy/metrics/de_sitter_3.py
riccipy/metrics/domain_wall.py
riccipy/metrics/dunn_tupper.py
riccipy/metrics/durgapal_1.py
riccipy/metrics/durgapal_2.py
riccipy/metrics/durgapal_3.py
riccipy/metrics/durgapal_fuloria.py
riccipy/metrics/einstein_1.py
riccipy/metrics/einstein_2.py
riccipy/metrics/einstein_3.py
riccipy/metrics/einstein_maxwell_1.py
riccipy/metrics/einstein_maxwell_2.py
riccipy/metrics/einstein_maxwell_3.py
riccipy/metrics/ellis_maccallum_1.py
